aeque-0.1.0.dist-info/METADATA
aeque-0.1.0.dist-info/WHEEL
aeque-0.1.0.dist-info/licenses/LICENSE
aeque/__init__.py
aeque/__init__.pyi
aeque/py.typed
aeque/aeque.cpython-313-darwin.so
aeque-0.1.0.dist-info/RECORD
